geometor/explorer/__init__.py
geometor/explorer/__main__.py
geometor/explorer/app.py
geometor/explorer/log.py
geometor/explorer/serialize.py
geometor/explorer/static/favicon.ico
geometor/explorer/static/css/modal.css
geometor/explorer/static/css/style.css
geometor/explorer/static/css/svg.css
geometor/explorer/static/icons/delete.svg
geometor/explorer/static/icons/edit.svg
geometor/explorer/static/icons/expand.svg
geometor/explorer/static/icons/filter.svg
geometor/explorer/static/icons/new-file.svg
geometor/explorer/static/icons/open.svg
geometor/explorer/static/icons/save-as.svg
geometor/explorer/static/icons/save.svg
geometor/explorer/static/js/Animate.js
geometor/explorer/static/js/groups.js
geometor/explorer/static/js/main.js
geometor/explorer/static/js/modal.js
geometor/explorer/static/js/resizer.js
geometor/explorer/static/js/svg.js
geometor/explorer/templates/index.html
geometor_explorer-0.4.4.dist-info/licenses/LICENSE
geometor_explorer-0.4.4.dist-info/METADATA
geometor_explorer-0.4.4.dist-info/WHEEL
geometor_explorer-0.4.4.dist-info/entry_points.txt
geometor_explorer-0.4.4.dist-info/top_level.txt
geometor_explorer-0.4.4.dist-info/RECORD
