Metadata-Version: 2.4
Name: geometor-explorer
Version: 0.4.4
Summary: An interactive interface for visualizing and analyzing geometric models.
Author-email: geometor <github@geometor.com>
Project-URL: Website, https://geometor.github.io/explorer
Project-URL: Repository, https://github.com/geometor/explorer
Project-URL: Issues, https://github.com/geometor/explorer/issues
Classifier: Programming Language :: Python :: 3
Classifier: License :: OSI Approved :: MIT License
Classifier: Operating System :: OS Independent
Requires-Python: >=3.13
License-File: LICENSE
Requires-Dist: geometor-model
Requires-Dist: geometor-divine
Requires-Dist: rich
Requires-Dist: flask
Dynamic: license-file
